aiohttp_wsconnhandler/__init__.py
aiohttp_wsconnhandler/client_conn_initer.py
aiohttp_wsconnhandler/ws_conn_handler.py
aiohttp_wsconnhandler-0.2.0.dist-info/LICENSE
aiohttp_wsconnhandler-0.2.0.dist-info/METADATA
aiohttp_wsconnhandler-0.2.0.dist-info/WHEEL
aiohttp_wsconnhandler-0.2.0.dist-info/top_level.txt
aiohttp_wsconnhandler-0.2.0.dist-info/RECORD
